a28/envio no moodle/adder.v
module adder #(
    parameter N = 8
) (
    input  wire [N-1:0] a,
    input  wire [N-1:0] b,
    output wire [N-1:0] soma
);

    assign soma = a + b;

endmodule

a28/envio no moodle/registrador.v
module registrador #(
    parameter N = 8
) (
    input  wire clk,
    input  wire load,
    input  wire [N-1:0] d,
    output reg  [N-1:0] q
);

    always @(posedge clk) begin
        if (load) begin
            q <= d;
        end
    end

endmodule

a28/envio no moodle/mux2.v
module mux2 #(
    parameter N = 8
) (
    input  wire [N-1:0] I0,
    input  wire [N-1:0] I1,
    input  wire sel,
    output wire [N-1:0] y
);

    assign y = sel ? I1 : I0;

endmodule

a28/envio no moodle/fd.v
// Pedro Sousa Goularte - 16897265
// Lucas Belo - 9896862
// Lana Rodrigues - 17109767

module fd #(parameter n = 8) (
    input wire clk ,
    input wire LOADP , 
    input wire SELP , 
    input wire LOADA , 
    input wire SELA , 
    input wire LOADB , 
    input wire SELB , 
    input wire LOADN , 
    input wire SELN , 
    input wire [n -1:0] A , 
    input wire [n -1:0] B , 
    input wire [n -1:0] N , 
    output wire [2* n -1:0] P , 
    output wire [n -1:0] REGN_out , 
    output wire [n -1:0] REGB_out 
);

    //REGN e S2
    wire [n -1:0] muxn_out;
    wire [n -1:0] subn_out;
    
    mux2 #(.N(n)) mux_REGN (
        .I0(N),           
        .I1(subn_out),    
        .sel(SELN),
        .y(muxn_out)
    );

    wire [n - 1:0] regn_out;
    registrador #(.N(n)) REGN (
        .clk(clk),
        .load(LOADN),
        .d(muxn_out),
        .q(regn_out)
    );
    assign REGN_out = regn_out;

    adder #(.N(n)) S2 (
        .a(regn_out),
        .b({n{1'b1}}),
        .soma(subn_out)
    );

    //REGB 
    wire [n -1:0] shift_r_B;
    wire [n -1:0] regb_out;
    wire [n -1:0] muxb_out;

    mux2 #(.N(n)) mux_REGB (
        .I0(B),           
        .I1(shift_r_B),   
        .sel(SELB),
        .y(muxb_out)
    );

    registrador #(.N(n)) REGB (
        .clk(clk),
        .load(LOADB),
        .d(muxb_out),
        .q(regb_out)
    );
    
    assign shift_r_B = {1'b0, regb_out[n-1:1]}; 
    assign REGB_out = regb_out;


    //REGA
    wire [2*n -1:0] muxa_out;
    wire [2*n -1:0] rega_out;
    wire [2*n -1:0] shift_l_A;

    mux2 #(.N(2*n)) mux_REGA (
        .I0({{n{1'b0}}, A}), 
        .I1(shift_l_A),      
        .sel(SELA),
        .y(muxa_out)
    );

    registrador #(.N(2*n)) REGA (
        .clk(clk),
        .load(LOADA),
        .d(muxa_out),
        .q(rega_out)
    );
    
    assign shift_l_A = {rega_out[2*n-2:0], 1'b0}; 

    //REGP
    wire [2*n -1:0] muxp_out;
    wire [2*n -1:0] regp_out;
    wire [2*n -1:0] adder1_out;

    mux2 #(.N(2*n)) mux_REGP (
        .I0({(2*n){1'b0}}), 
        .I1(adder1_out),    
        .sel(SELP),
        .y(muxp_out)
    );

    registrador #(.N(2*n)) REGP (
        .clk(clk),
        .load(LOADP),
        .d(muxp_out),
        .q(regp_out)
    );
    assign P = regp_out;

    //S1
    adder #(.N(2*n)) S1 (
        .a(regp_out),
        .b(rega_out),
        .soma(adder1_out)
    );

endmodule

a28/envio no moodle/asm.v
// Pedro Sousa Goularte - 16897265
// Lucas Belo - 9896862
// Lana Rodrigues - 17109767

/* Flip-flop tipo D com reset e preset assíncronos */
module estado (
    input clk, rst, prt, d,
    output reg q
);
    always @(posedge clk, posedge rst, posedge prt) begin
        if (rst)
            q <= 1'b0;
        else if (prt)
            q <= 1'b1;
        else
            q <= d;
    end
endmodule

/* DEMUX 1 para 2 */
module decisor (
    input ativacao,
    input x,
    output x0, x1
);
    assign x0 = ativacao & ~x;
    assign x1 = ativacao & x;
endmodule

/* OR de N entradas */
module juncao #(
    parameter N = 2
) (
    input [N-1:0] in,
    output out
);
    assign out = |in;
endmodule

module detector_asm (
    input clk, rst, x,
    output detected
);


endmodule

module uc #(
    parameter n = 8
) (
    input wire clk,
    input wire reset,
    input wire init,
    input wire [n-1:0] N, // Contador de iterações
    input wire [n-1:0] B, // Bit menos significativo do multiplicador (B[0])
    output reg SELA, // Seleção de entrada para o registrador A (0: Entrada A; 1: Shift Left)
    output reg SELB, // Seleção de entrada para o registrador B (0: Entrada B; 1: Shift Right)
    output reg SELP, // Seleção de entrada para o registrador P (0: 0; 1: P + A)
    output reg SELN, // Seleção de entrada para o registrador N (0: Entrada N; 1: N - 1)
    output reg LOADA, // Sinal de carga para o registrador A
    output reg LOADB, // Sinal de carga para o registrador B
    output reg LOADP, // Sinal de carga para o registrador P
    output reg LOADN, // Sinal de carga para o registrador N
    output reg finish // Sinal de término da operação
);

    localparam S0 = 3'd0; 
    localparam S1 = 3'd1;
    localparam S2 = 3'd2;
    localparam S3 = 3'd3; 
    localparam S4 = 3'd4; 
    localparam S5 = 3'd5;
    localparam S6 = 3'd6; 

    reg [2:0] state, next_state;

    // Registrador de Estado
    always @(posedge clk or posedge reset) begin
        if (reset)
            state <= S0;
        else
            state <= next_state;
    end

    // Lógica do Próximo Estado e Saídas 
    always @(*) begin
        next_state = state;
        // Valores padrão 
        SELA = 0; SELB = 0; SELP = 0; SELN = 0;
        LOADA = 0; LOADB = 0; LOADP = 0; LOADN = 0;
        finish = 0;

        case (state)
            S0: begin 
                if (init) next_state = S1;
            end

            S1: begin
                // Carrega entradas e zera P
                LOADA = 1; SELA = 0; 
                LOADB = 1; SELB = 0; 
                LOADN = 1; SELN = 0; 
                LOADP = 1; SELP  = 0; // Seleciona 0 para zerar P

                next_state = S2;
            end

            S2: begin 
                if (N > 0)
                    next_state = S3;
                else
                    next_state = S6; 
            end

            S3: begin 
                if (B[0] == 1'b1)
                    next_state = S4; // Adiciona se B[0] == 1
                else
                    next_state = S5; // Apenas desloca se B[0] == 0
            end

            S4: begin
                LOADP = 1;
                SELP  = 1; // Seleciona P + A
                
                next_state = S5;
            end

            S5: begin
                LOADA = 1; SELA = 1; // A << 1
                LOADB = 1; SELB = 1; // B >> 1
                LOADN = 1; SELN = 1; // N - 1
                
                next_state = S2; 
            end

            S6: begin
                finish = 1;
                next_state = S0; // Volta
            end

            default: next_state = S0;
        endcase
    end

endmodule

a28/envio no moodle/multiplicador.v
// Pedro Sousa Goularte - 16897265
// Lucas Belo - 9896862
// Lana Rodrigues - 17109767

module multiplicador #(parameter n = 8) (
    input wire clk ,
    input wire reset ,
    input wire init ,
    input wire [n -1:0] A ,
    input wire [n -1:0] B ,
    input wire [n -1:0] N ,
    output wire [2* n -1:0] P ,
    output wire finish
);
    wire loadp;
    wire selp;
    wire loada;
    wire sela;
    wire loadb;
    wire selb;
    wire loadn;
    wire seln;

    wire [n -1:0] reg_b;
    wire [n -1:0] reg_n;

    uc #(.n(n)) unidade_controle (
        .clk(clk),
        .reset(reset), 
        .init(init),       
        .N(reg_n), 
        .B(reg_b), 

        .SELA(sela),
        .SELB(selb),
        .SELP(selp),
        .SELN(seln),
        .LOADA(loada),
        .LOADB(loadb),
        .LOADP(loadp),
        .LOADN(loadn),
        .finish(finish)
    );

    fd #(.n(n)) fluxo_dados (
        .clk(clk),
        .LOADP(loadp),
        .SELP(selp),
        .LOADA(loada),
        .SELA(sela),
        .LOADB(loadb),
        .SELB(selb),
        .LOADN(loadn),
        .SELN(seln),
        .A(A),
        .B(B),
        .N(N),

        .P(P),
        .REGN_out(reg_n),
        .REGB_out(reg_b)
    );

endmodule

a28/envio no moodle/tb_multiplicador.v
`timescale 1ns/1ps

module tb_multiplicador;

    // Parâmetros
    parameter n = 8;

    // Sinais de entrada (Regs)
    reg clk;
    reg reset;
    reg init;
    reg [n-1:0] A;
    reg [n-1:0] B;
    reg [n-1:0] N;

    // Sinais de saída (Wires)
    wire [2*n-1:0] P;
    wire finish;

    // Instanciação do Módulo Principal (DUT)
    multiplicador #(.n(n)) dut (
        .clk(clk),
        .reset(reset),
        .init(init),
        .A(A),
        .B(B),
        .N(N),
        .P(P),
        .finish(finish)
    );

    // Geração de Clock (Período = 10ns)
    always #5 clk = ~clk;

    // Configuração do VCD para GTKWave
    initial begin
        // Nome do arquivo de saída
        $dumpfile("sinal.vcd");
        // Nível 0 = Salva todos os sinais hierarquicamente abaixo de tb_multiplicador
        $dumpvars(0, tb_multiplicador);
    end

    // Procedimento de Teste
    initial begin
        // 1. Inicialização
        clk = 0;
        reset = 1;
        init = 0;
        A = 0; B = 0; N = 0;

        // Solta o reset após alguns ciclos
        #15 reset = 0;

        // -------------------------------------------------
        // CASO DE TESTE 1: 6 * 7 = 42 (Pequenos números)
        // -------------------------------------------------
        #20;
        $display("--- Inicio Teste 1: 6 x 7 ---");
        A = 8'd6;
        B = 8'd7;
        N = 8'd8; // Número de iterações (bits)

        // Pulso de INIT (exatamente 1 ciclo de clock)
        @(posedge clk);
        init = 1;
        @(posedge clk);
        init = 0;

        // Aguarda o sinal de finish
        wait(finish == 1);
        
        // Pequeno delay para estabilização visual na onda
        #10; 

        // Verificação automática
        if (P === 42) 
            $display("[SUCESSO] 6 * 7 = %d", P);
        else 
            $display("[ERRO] 6 * 7 = %d (Esperado: 42)", P);


        // -------------------------------------------------
        // CASO DE TESTE 2: 255 * 255 (Limite máximo de 8 bits)
        // -------------------------------------------------
        #20;
        $display("\n--- Inicio Teste 2: 255 x 255 ---");
        A = 8'd255;
        B = 8'd255;
        N = 8'd8;

        // Pulso de INIT
        @(posedge clk);
        init = 1;
        @(posedge clk);
        init = 0;

        wait(finish == 1);
        #10;

        if (P === 65025) 
            $display("[SUCESSO] 255 * 255 = %d", P);
        else 
            $display("[ERRO] 255 * 255 = %d (Esperado: 65025)", P);


        // -------------------------------------------------
        // CASO DE TESTE 3: Multiplicação por Zero (200 * 0 = 0)
        // -------------------------------------------------
        #20;
        $display("\n--- Inicio Teste 3: 200 x 0 ---");
        A = 8'd200;
        B = 8'd0;
        N = 8'd8;

        // Pulso de INIT
        @(posedge clk);
        init = 1;
        @(posedge clk);
        init = 0;

        wait(finish == 1);
        #10;

        if (P === 0) 
            $display("[SUCESSO] 200 * 0 = %d", P);
        else 
            $display("[ERRO] 200 * 0 = %d (Esperado: 0)", P);


        // -------------------------------------------------
        // CASO DE TESTE 4: Multiplicação por Um (1 * 150 = 150)
        // -------------------------------------------------
        #20;
        $display("\n--- Inicio Teste 4: 1 x 150 ---");
        A = 8'd1;
        B = 8'd150;
        N = 8'd8;

        // Pulso de INIT
        @(posedge clk);
        init = 1;
        @(posedge clk);
        init = 0;

        wait(finish == 1);
        #10;

        if (P === 150) 
            $display("[SUCESSO] 1 * 150 = %d", P);
        else 
            $display("[ERRO] 1 * 150 = %d (Esperado: 150)", P);


        // -------------------------------------------------
        // CASO DE TESTE 5: Intermediário (100 * 3 = 300)
        // -------------------------------------------------
        #20;
        $display("\n--- Inicio Teste 5: 100 x 3 ---");
        A = 8'd100;
        B = 8'd3;
        N = 8'd8;

        // Pulso de INIT
        @(posedge clk);
        init = 1;
        @(posedge clk);
        init = 0;

        wait(finish == 1);
        #10;

        if (P === 300) 
            $display("[SUCESSO] 100 * 3 = %d", P);
        else 
            $display("[ERRO] 100 * 3 = %d (Esperado: 300)", P);


        // Finaliza a simulação
        #50;
        $finish;
    end

    // Monitoramento no console (Opcional)
    initial begin
        // Mostra alterações no estado da UC e nos registradores principais
        // Atenção: Esta linha requer que os módulos internos (unidade_controle, fluxo_dados, REGN)
        // existam e que o DUT seja instanciado com o nome 'dut'.
        $monitor("Time=%0t | State=%d | N=%d | P=%d | Finish=%b", 
                  $time, dut.unidade_controle.state, dut.fluxo_dados.REGN.q, P, finish);
    end

endmodule

a28/envio no moodle/sinal.vcd
$date
	Mon Nov 24 17:07:42 2025
$end
$version
	Icarus Verilog
$end
$timescale
	1ps
$end
$scope module tb_multiplicador $end
$var wire 1 ! finish $end
$var wire 16 " P [15:0] $end
$var parameter 32 # n $end
$var reg 8 $ A [7:0] $end
$var reg 8 % B [7:0] $end
$var reg 8 & N [7:0] $end
$var reg 1 ' clk $end
$var reg 1 ( init $end
$var reg 1 ) reset $end
$scope module dut $end
$var wire 8 * A [7:0] $end
$var wire 8 + B [7:0] $end
$var wire 8 , N [7:0] $end
$var wire 1 ' clk $end
$var wire 1 ( init $end
$var wire 1 ) reset $end
$var wire 1 - selp $end
$var wire 1 . seln $end
$var wire 1 / selb $end
$var wire 1 0 sela $end
$var wire 8 1 reg_n [7:0] $end
$var wire 8 2 reg_b [7:0] $end
$var wire 1 3 loadp $end
$var wire 1 4 loadn $end
$var wire 1 5 loadb $end
$var wire 1 6 loada $end
$var wire 1 ! finish $end
$var wire 16 7 P [15:0] $end
$var parameter 32 8 n $end
$scope module fluxo_dados $end
$var wire 8 9 A [7:0] $end
$var wire 8 : B [7:0] $end
$var wire 8 ; N [7:0] $end
$var wire 16 < P [15:0] $end
$var wire 8 = REGB_out [7:0] $end
$var wire 8 > REGN_out [7:0] $end
$var wire 1 ' clk $end
$var wire 8 ? subn_out [7:0] $end
$var wire 8 @ shift_r_B [7:0] $end
$var wire 16 A shift_l_A [15:0] $end
$var wire 16 B regp_out [15:0] $end
$var wire 8 C regn_out [7:0] $end
$var wire 8 D regb_out [7:0] $end
$var wire 16 E rega_out [15:0] $end
$var wire 16 F muxp_out [15:0] $end
$var wire 8 G muxn_out [7:0] $end
$var wire 8 H muxb_out [7:0] $end
$var wire 16 I muxa_out [15:0] $end
$var wire 16 J adder1_out [15:0] $end
$var wire 1 - SELP $end
$var wire 1 . SELN $end
$var wire 1 / SELB $end
$var wire 1 0 SELA $end
$var wire 1 3 LOADP $end
$var wire 1 4 LOADN $end
$var wire 1 5 LOADB $end
$var wire 1 6 LOADA $end
$var parameter 32 K n $end
$scope module REGA $end
$var wire 1 ' clk $end
$var wire 1 6 load $end
$var wire 16 L d [15:0] $end
$var parameter 64 M N $end
$var reg 16 N q [15:0] $end
$upscope $end
$scope module REGB $end
$var wire 1 ' clk $end
$var wire 1 5 load $end
$var wire 8 O d [7:0] $end
$var parameter 32 P N $end
$var reg 8 Q q [7:0] $end
$upscope $end
$scope module REGN $end
$var wire 1 ' clk $end
$var wire 1 4 load $end
$var wire 8 R d [7:0] $end
$var parameter 32 S N $end
$var reg 8 T q [7:0] $end
$upscope $end
$scope module REGP $end
$var wire 1 ' clk $end
$var wire 1 3 load $end
$var wire 16 U d [15:0] $end
$var parameter 64 V N $end
$var reg 16 W q [15:0] $end
$upscope $end
$scope module S1 $end
$var wire 16 X a [15:0] $end
$var wire 16 Y b [15:0] $end
$var wire 16 Z soma [15:0] $end
$var parameter 64 [ N $end
$upscope $end
$scope module S2 $end
$var wire 8 \ a [7:0] $end
$var wire 8 ] b [7:0] $end
$var wire 8 ^ soma [7:0] $end
$var parameter 32 _ N $end
$upscope $end
$scope module mux_REGA $end
$var wire 16 ` I0 [15:0] $end
$var wire 16 a I1 [15:0] $end
$var wire 16 b y [15:0] $end
$var wire 1 0 sel $end
$var parameter 64 c N $end
$upscope $end
$scope module mux_REGB $end
$var wire 8 d I0 [7:0] $end
$var wire 8 e I1 [7:0] $end
$var wire 8 f y [7:0] $end
$var wire 1 / sel $end
$var parameter 32 g N $end
$upscope $end
$scope module mux_REGN $end
$var wire 8 h I0 [7:0] $end
$var wire 8 i I1 [7:0] $end
$var wire 8 j y [7:0] $end
$var wire 1 . sel $end
$var parameter 32 k N $end
$upscope $end
$scope module mux_REGP $end
$var wire 16 l I0 [15:0] $end
$var wire 16 m I1 [15:0] $end
$var wire 16 n y [15:0] $end
$var wire 1 - sel $end
$var parameter 64 o N $end
$upscope $end
$upscope $end
$scope module unidade_controle $end
$var wire 8 p B [7:0] $end
$var wire 8 q N [7:0] $end
$var wire 1 ' clk $end
$var wire 1 ( init $end
$var wire 1 ) reset $end
$var parameter 3 r S0 $end
$var parameter 3 s S1 $end
$var parameter 3 t S2 $end
$var parameter 3 u S3 $end
$var parameter 3 v S4 $end
$var parameter 3 w S5 $end
$var parameter 3 x S6 $end
$var parameter 32 y n $end
$var reg 1 6 LOADA $end
$var reg 1 5 LOADB $end
$var reg 1 4 LOADN $end
$var reg 1 3 LOADP $end
$var reg 1 0 SELA $end
$var reg 1 / SELB $end
$var reg 1 . SELN $end
$var reg 1 - SELP $end
$var reg 1 ! finish $end
$var reg 3 z next_state [2:0] $end
$var reg 3 { state [2:0] $end
$upscope $end
$upscope $end
$upscope $end
$enddefinitions $end
$comment Show the parameter values. $end
$dumpall
b1000 y
b110 x
b101 w
b100 v
b11 u
b10 t
b1 s
b0 r
b10000 o
b1000 k
b1000 g
b10000 c
b1000 _
b10000 [
b10000 V
b1000 S
b1000 P
b10000 M
b1000 K
b1000 8
b1000 #
$end
#0
$dumpvars
b0 {
b0 z
bx q
bx p
b0 n
bx m
b0 l
b0 j
bx i
b0 h
b0 f
b0xxxxxxx e
b0 d
b0 b
bx0 a
b0 `
bx ^
b11111111 ]
bx \
bx Z
bx Y
bx X
bx W
b0 U
bx T
b0 R
bx Q
b0 O
bx N
b0 L
bx J
b0 I
b0 H
b0 G
b0 F
bx E
bx D
bx C
bx B
bx0 A
b0xxxxxxx @
bx ?
bx >
bx =
bx <
b0 ;
b0 :
b0 9
bx 7
06
05
04
03
bx 2
bx 1
00
0/
0.
0-
b0 ,
b0 +
b0 *
1)
0(
0'
b0 &
b0 %
b0 $
bx "
0!
$end
#5000
1'
#10000
0'
#15000
1'
0)
#20000
0'
#25000
1'
#30000
0'
#35000
b1 z
1(
b1000 G
b1000 R
b1000 j
b111 H
b111 O
b111 f
b110 I
b110 L
b110 b
1'
b1000 &
b1000 ,
b1000 ;
b1000 h
b111 %
b111 +
b111 :
b111 d
b110 `
b110 $
b110 *
b110 9
#40000
0'
#45000
13
14
15
16
b1 {
b10 z
0(
1'
#50000
0'
#55000
b1100 A
b1100 a
b11 @
b11 e
b11 z
04
03
05
06
b110 J
b110 Z
b110 m
b0 "
b0 7
b0 <
b0 B
b0 W
b0 X
b110 E
b110 N
b110 Y
b111 2
b111 =
b111 p
b111 D
b111 Q
b111 ?
b111 ^
b111 i
b1000 1
b1000 >
b1000 q
b1000 C
b1000 T
b1000 \
b10 {
1'
#60000
0'
#65000
b100 z
b11 {
1'
#70000
0'
#75000
b110 F
b110 U
b110 n
b101 z
1-
13
b100 {
1'
#80000
0'
#85000
b111 G
b111 R
b111 j
b11 H
b11 O
b11 f
b1100 I
b1100 L
b1100 b
b0 F
b0 U
b0 n
b10 z
1.
14
1/
15
10
16
03
0-
b1100 J
b1100 Z
b1100 m
b110 "
b110 7
b110 <
b110 B
b110 W
b110 X
b101 {
1'
#90000
0'
#95000
b111 H
b111 O
b111 f
b110 I
b110 L
b110 b
b11000 A
b11000 a
b1 @
b1 e
b1000 G
b1000 R
b1000 j
b11 z
04
05
06
0.
0/
00
b10010 J
b10010 Z
b10010 m
b1100 E
b1100 N
b1100 Y
b11 2
b11 =
b11 p
b11 D
b11 Q
b110 ?
b110 ^
b110 i
b111 1
b111 >
b111 q
b111 C
b111 T
b111 \
b10 {
1'
#100000
0'
#105000
b100 z
b11 {
1'
#110000
0'
#115000
b10010 F
b10010 U
b10010 n
b101 z
1-
13
b100 {
1'
#120000
0'
#125000
b110 G
b110 R
b110 j
b1 H
b1 O
b1 f
b11000 I
b11000 L
b11000 b
b0 F
b0 U
b0 n
b10 z
1.
14
1/
15
10
16
03
0-
b11110 J
b11110 Z
b11110 m
b10010 "
b10010 7
b10010 <
b10010 B
b10010 W
b10010 X
b101 {
1'
#130000
0'
#135000
b111 H
b111 O
b111 f
b110 I
b110 L
b110 b
b110000 A
b110000 a
b0 @
b0 e
b1000 G
b1000 R
b1000 j
b11 z
04
05
06
0.
0/
00
b101010 J
b101010 Z
b101010 m
b11000 E
b11000 N
b11000 Y
b1 2
b1 =
b1 p
b1 D
b1 Q
b101 ?
b101 ^
b101 i
b110 1
b110 >
b110 q
b110 C
b110 T
b110 \
b10 {
1'
#140000
0'
#145000
b100 z
b11 {
1'
#150000
0'
#155000
b101010 F
b101010 U
b101010 n
b101 z
1-
13
b100 {
1'
#160000
0'
#165000
b101 G
b101 R
b101 j
b0 H
b0 O
b0 f
b110000 I
b110000 L
b110000 b
b0 F
b0 U
b0 n
b10 z
1.
14
1/
15
10
16
03
0-
b1000010 J
b1000010 Z
b1000010 m
b101010 "
b101010 7
b101010 <
b101010 B
b101010 W
b101010 X
b101 {
1'
#170000
0'
#175000
b111 H
b111 O
b111 f
b110 I
b110 L
b110 b
b1100000 A
b1100000 a
b1000 G
b1000 R
b1000 j
b11 z
04
05
06
0.
0/
00
b1011010 J
b1011010 Z
b1011010 m
b110000 E
b110000 N
b110000 Y
b0 2
b0 =
b0 p
b0 D
b0 Q
b100 ?
b100 ^
b100 i
b101 1
b101 >
b101 q
b101 C
b101 T
b101 \
b10 {
1'
#180000
0'
#185000
b101 z
b11 {
1'
#190000
0'
#195000
b100 G
b100 R
b100 j
b0 H
b0 O
b0 f
b1100000 I
b1100000 L
b1100000 b
b10 z
1.
14
1/
15
10
16
b101 {
1'
#200000
0'
#205000
b111 H
b111 O
b111 f
b110 I
b110 L
b110 b
b1000 G
b1000 R
b1000 j
b11000000 A
b11000000 a
b11 z
04
05
06
0.
0/
00
b11 ?
b11 ^
b11 i
b100 1
b100 >
b100 q
b100 C
b100 T
b100 \
b10001010 J
b10001010 Z
b10001010 m
b1100000 E
b1100000 N
b1100000 Y
b10 {
1'
#210000
0'
#215000
b101 z
b11 {
1'
#220000
0'
#225000
b11 G
b11 R
b11 j
b0 H
b0 O
b0 f
b11000000 I
b11000000 L
b11000000 b
b10 z
1.
14
1/
15
10
16
b101 {
1'
#230000
0'
#235000
b111 H
b111 O
b111 f
b110 I
b110 L
b110 b
b110000000 A
b110000000 a
b1000 G
b1000 R
b1000 j
b11 z
04
05
06
0.
0/
00
b11101010 J
b11101010 Z
b11101010 m
b11000000 E
b11000000 N
b11000000 Y
b10 ?
b10 ^
b10 i
b11 1
b11 >
b11 q
b11 C
b11 T
b11 \
b10 {
1'
#240000
0'
#245000
b101 z
b11 {
1'
#250000
0'
#255000
b10 G
b10 R
b10 j
b0 H
b0 O
b0 f
b110000000 I
b110000000 L
b110000000 b
b10 z
1.
14
1/
15
10
16
b101 {
1'
#260000
0'
#265000
b111 H
b111 O
b111 f
b110 I
b110 L
b110 b
b1000 G
b1000 R
b1000 j
b1100000000 A
b1100000000 a
b11 z
04
05
06
0.
0/
00
b1 ?
b1 ^
b1 i
b10 1
b10 >
b10 q
b10 C
b10 T
b10 \
b110101010 J
b110101010 Z
b110101010 m
b110000000 E
b110000000 N
b110000000 Y
b10 {
1'
#270000
0'
#275000
b101 z
b11 {
1'
#280000
0'
#285000
b1 G
b1 R
b1 j
b0 H
b0 O
b0 f
b1100000000 I
b1100000000 L
b1100000000 b
b10 z
1.
14
1/
15
10
16
b101 {
1'
#290000
0'
#295000
b111 H
b111 O
b111 f
b110 I
b110 L
b110 b
b11000000000 A
b11000000000 a
b1000 G
b1000 R
b1000 j
b11 z
04
05
06
0.
0/
00
b1100101010 J
b1100101010 Z
b1100101010 m
b1100000000 E
b1100000000 N
b1100000000 Y
b0 ?
b0 ^
b0 i
b1 1
b1 >
b1 q
b1 C
b1 T
b1 \
b10 {
1'
#300000
0'
#305000
b101 z
b11 {
1'
#310000
0'
#315000
b0 G
b0 R
b0 j
b0 H
b0 O
b0 f
b11000000000 I
b11000000000 L
b11000000000 b
b10 z
1.
14
1/
15
10
16
b101 {
1'
#320000
0'
#325000
b111 H
b111 O
b111 f
b110 I
b110 L
b110 b
b1000 G
b1000 R
b1000 j
b110000000000 A
b110000000000 a
b110 z
04
05
06
0.
0/
00
b11111111 ?
b11111111 ^
b11111111 i
b0 1
b0 >
b0 q
b0 C
b0 T
b0 \
b11000101010 J
b11000101010 Z
b11000101010 m
b11000000000 E
b11000000000 N
b11000000000 Y
b10 {
1'
#330000
0'
#335000
b0 z
1!
b110 {
1'
#340000
0'
#345000
0!
b0 {
1'
#350000
0'
#355000
1'
#360000
0'
#365000
b1 z
1(
b11111111 H
b11111111 O
b11111111 f
b11111111 I
b11111111 L
b11111111 b
1'
b11111111 %
b11111111 +
b11111111 :
b11111111 d
b11111111 `
b11111111 $
b11111111 *
b11111111 9
#370000
0'
#375000
13
14
15
16
b1 {
b10 z
0(
1'
#380000
0'
#385000
b1111111 @
b1111111 e
b111111110 A
b111111110 a
b11 z
04
03
05
06
b111 ?
b111 ^
b111 i
b1000 1
b1000 >
b1000 q
b1000 C
b1000 T
b1000 \
b11111111 2
b11111111 =
b11111111 p
b11111111 D
b11111111 Q
b11111111 E
b11111111 N
b11111111 Y
b11111111 J
b11111111 Z
b11111111 m
b0 "
b0 7
b0 <
b0 B
b0 W
b0 X
b10 {
1'
#390000
0'
#395000
b100 z
b11 {
1'
#400000
0'
#405000
b11111111 F
b11111111 U
b11111111 n
b101 z
1-
13
b100 {
1'
#410000
0'
#415000
b111 G
b111 R
b111 j
b1111111 H
b1111111 O
b1111111 f
b111111110 I
b111111110 L
b111111110 b
b0 F
b0 U
b0 n
b10 z
1.
14
1/
15
10
16
03
0-
b111111110 J
b111111110 Z
b111111110 m
b11111111 "
b11111111 7
b11111111 <
b11111111 B
b11111111 W
b11111111 X
b101 {
1'
#420000
0'
#425000
b11111111 H
b11111111 O
b11111111 f
b11111111 I
b11111111 L
b11111111 b
b1000 G
b1000 R
b1000 j
b111111 @
b111111 e
b1111111100 A
b1111111100 a
b11 z
04
05
06
0.
0/
00
b110 ?
b110 ^
b110 i
b111 1
b111 >
b111 q
b111 C
b111 T
b111 \
b1111111 2
b1111111 =
b1111111 p
b1111111 D
b1111111 Q
b1011111101 J
b1011111101 Z
b1011111101 m
b111111110 E
b111111110 N
b111111110 Y
b10 {
1'
#430000
0'
#435000
b100 z
b11 {
1'
#440000
0'
#445000
b1011111101 F
b1011111101 U
b1011111101 n
b101 z
1-
13
b100 {
1'
#450000
0'
#455000
b110 G
b110 R
b110 j
b111111 H
b111111 O
b111111 f
b1111111100 I
b1111111100 L
b1111111100 b
b0 F
b0 U
b0 n
b10 z
1.
14
1/
15
10
16
03
0-
b10011111011 J
b10011111011 Z
b10011111011 m
b1011111101 "
b1011111101 7
b1011111101 <
b1011111101 B
b1011111101 W
b1011111101 X
b101 {
1'
#460000
0'
#465000
b11111111 H
b11111111 O
b11111111 f
b11111111 I
b11111111 L
b11111111 b
b1000 G
b1000 R
b1000 j
b11111 @
b11111 e
b11111111000 A
b11111111000 a
b11 z
04
05
06
0.
0/
00
b101 ?
b101 ^
b101 i
b110 1
b110 >
b110 q
b110 C
b110 T
b110 \
b111111 2
b111111 =
b111111 p
b111111 D
b111111 Q
b11011111001 J
b11011111001 Z
b11011111001 m
b1111111100 E
b1111111100 N
b1111111100 Y
b10 {
1'
#470000
0'
#475000
b100 z
b11 {
1'
#480000
0'
#485000
b11011111001 F
b11011111001 U
b11011111001 n
b101 z
1-
13
b100 {
1'
#490000
0'
#495000
b101 G
b101 R
b101 j
b11111 H
b11111 O
b11111 f
b11111111000 I
b11111111000 L
b11111111000 b
b0 F
b0 U
b0 n
b10 z
1.
14
1/
15
10
16
03
0-
b101011110101 J
b101011110101 Z
b101011110101 m
b11011111001 "
b11011111001 7
b11011111001 <
b11011111001 B
b11011111001 W
b11011111001 X
b101 {
1'
#500000
0'
#505000
b11111111 H
b11111111 O
b11111111 f
b11111111 I
b11111111 L
b11111111 b
b1000 G
b1000 R
b1000 j
b1111 @
b1111 e
b111111110000 A
b111111110000 a
b11 z
04
05
06
0.
0/
00
b100 ?
b100 ^
b100 i
b101 1
b101 >
b101 q
b101 C
b101 T
b101 \
b11111 2
b11111 =
b11111 p
b11111 D
b11111 Q
b111011110001 J
b111011110001 Z
b111011110001 m
b11111111000 E
b11111111000 N
b11111111000 Y
b10 {
1'
#510000
0'
#515000
b100 z
b11 {
1'
#520000
0'
#525000
b111011110001 F
b111011110001 U
b111011110001 n
b101 z
1-
13
b100 {
1'
#530000
0'
#535000
b100 G
b100 R
b100 j
b1111 H
b1111 O
b1111 f
b111111110000 I
b111111110000 L
b111111110000 b
b0 F
b0 U
b0 n
b10 z
1.
14
1/
15
10
16
03
0-
b1011011101001 J
b1011011101001 Z
b1011011101001 m
b111011110001 "
b111011110001 7
b111011110001 <
b111011110001 B
b111011110001 W
b111011110001 X
b101 {
1'
#540000
0'
#545000
b11111111 H
b11111111 O
b11111111 f
b11111111 I
b11111111 L
b11111111 b
b1000 G
b1000 R
b1000 j
b111 @
b111 e
b1111111100000 A
b1111111100000 a
b11 z
04
05
06
0.
0/
00
b11 ?
b11 ^
b11 i
b100 1
b100 >
b100 q
b100 C
b100 T
b100 \
b1111 2
b1111 =
b1111 p
b1111 D
b1111 Q
b1111011100001 J
b1111011100001 Z
b1111011100001 m
b111111110000 E
b111111110000 N
b111111110000 Y
b10 {
1'
#550000
0'
#555000
b100 z
b11 {
1'
#560000
0'
#565000
b1111011100001 F
b1111011100001 U
b1111011100001 n
b101 z
1-
13
b100 {
1'
#570000
0'
#575000
b11 G
b11 R
b11 j
b111 H
b111 O
b111 f
b1111111100000 I
b1111111100000 L
b1111111100000 b
b0 F
b0 U
b0 n
b10 z
1.
14
1/
15
10
16
03
0-
b10111011010001 J
b10111011010001 Z
b10111011010001 m
b1111011100001 "
b1111011100001 7
b1111011100001 <
b1111011100001 B
b1111011100001 W
b1111011100001 X
b101 {
1'
#580000
0'
