a16/tb_rc.v
// NOT: 2
// XOR2: 12
// XOR3: 20
// FI AND OR
// 2  7   8
// 3  10  12
// 4  13  16
// 5  16  20
// 6  19  24
// 7  22 
// 8  25

module cla8t (
    input [7:0] a,
    input [7:0] b,
    input cin,
    output [7:0] sum,
    output cout
);

    // Sinais internos para generate (G) e propagate (P)
    wire [7:0] g, p;
    wire [7:0] c;
    
    // Calcular Generate (G) e Propagate (P) para cada bit
    assign #7 g = a & b;  // G = A AND B
    assign #8 p = a | b;  // P = A OR B
    
    // Cálculo dos carries usando lookahead
    assign #0 c[0] = cin;
    assign #(8+7) c[1] = 
        g[0] | (p[0] & c[0]);
    assign #(12+10) c[2] = 
        g[1] | (p[1] & g[0]) | (p[1] & p[0] & c[0]);
    assign #(16+13) c[3] = 
        g[2] | (p[2] & g[1]) | (p[2] & p[1] & g[0]) | (p[2] & p[1] & p[0] & c[0]);
    assign #(20+16) c[4] = 
        g[3] | (p[3] & g[2]) | (p[3] & p[2] & g[1]) | 
        (p[3] & p[2] & p[1] & g[0]) | (p[3] & p[2] & p[1] & p[0] & c[0]);
    assign #(24+19) c[5] = 
        g[4] | (p[4] & g[3]) | (p[4] & p[3] & g[2]) | 
        (p[4] & p[3] & p[2] & g[1]) | (p[4] & p[3] & p[2] & p[1] & g[0]) |
        (p[4] & p[3] & p[2] & p[1] & p[0] & c[0]);
    assign #(24+8+22) c[6] = 
        g[5] | (p[5] & g[4]) | (p[5] & p[4] & g[3]) | 
        (p[5] & p[4] & p[3] & g[2]) | (p[5] & p[4] & p[3] & p[2] & g[1]) |
        (p[5] & p[4] & p[3] & p[2] & p[1] & g[0]) |
        (p[5] & p[4] & p[3] & p[2] & p[1] & p[0] & c[0]);
    assign #(24+12+25) c[7] = 
        g[6] | (p[6] & g[5]) | (p[6] & p[5] & g[4]) | 
        (p[6] & p[5] & p[4] & g[3]) | (p[6] & p[5] & p[4] & p[3] & g[2]) |
        (p[6] & p[5] & p[4] & p[3] & p[2] & g[1]) |
        (p[6] & p[5] & p[4] & p[3] & p[2] & p[1] & g[0]) |
        (p[6] & p[5] & p[4] & p[3] & p[2] & p[1] & p[0] & c[0]);
    
    // Carry de saída
    assign #(8+7) cout = g[7] | (p[7] & c[7]);
    
    // Cálculo da soma
    assign #(20) sum = a ^ b ^ c[7:0];

endmodule



module tb_carry_lookahead_adder;
    reg [7:0] a, b;
    reg cin;
    wire [7:0] sum;
    wire cout;
    reg [7:0] esperado_sum;
    reg esperado_cout;
    
    // Instanciar o somador
    cla8t dut (
        .a(a),
        .b(b),
        .cin(cin),
        .sum(sum),
        .cout(cout)
    );
    
    initial begin
        $dumpfile("somador.vcd");
        $dumpvars(0,tb_carry_lookahead_adder);

        // 1) Inicializar entradas
        a = 8'b0;
        b = 8'b0;
        cin = 0;
        esperado_sum = 8'b00000000;
        esperado_cout = 0;
        #1000;

        $display("1) esperado_sum=%b | obtido_soma=%b | %s", esperado_sum, sum, (sum == esperado_sum) ? "OK" : "ERRO");
        $display("1) esperado_cout=%b | obtido_cout=%b | %s", esperado_cout, cout, (cout == esperado_cout) ? "OK" : "ERRO");

        // 2) Overflow a
        a = 8'b11111111;
        b = 8'b0;
        cin = 1;
        esperado_sum = 8'b00000000;
        esperado_cout = 1;
        #1000;

        $display("2) esperado_sum=%b | obtido_soma=%b | %s", esperado_sum, sum, (sum == esperado_sum) ? "OK" : "ERRO");
        $display("2) esperado_cout=%b | obtido_cout=%b | %s", esperado_cout, cout, (cout == esperado_cout) ? "OK" : "ERRO");

        // 3) Overflow b
        a = 8'b0;
        b = 8'b11111111;
        cin = 1;
        esperado_sum = 8'b00000000;
        esperado_cout = 1;
        #1000;

        $display("3) esperado_sum=%b | obtido_soma=%b | %s", esperado_sum, sum, (sum == esperado_sum) ? "OK" : "ERRO");
        $display("3) esperado_cout=%b | obtido_cout=%b | %s", esperado_cout, cout, (cout == esperado_cout) ? "OK" : "ERRO");

        // 4) Overflow
        a = 8'b11111111;
        b = 8'b11111111;
        cin = 0;
        esperado_sum = 8'b11111110;
        esperado_cout = 1;
        #1000;

        $display("4) esperado_sum=%b | obtido_soma=%b | %s", esperado_sum, sum, (sum == esperado_sum) ? "OK" : "ERRO");
        $display("4) esperado_cout=%b | obtido_cout=%b | %s", esperado_cout, cout, (cout == esperado_cout) ? "OK" : "ERRO");

        // 5) Overflow
        a = 8'b11111111;
        b = 8'b11111111;
        cin = 1;
        esperado_sum = 8'b11111111;
        esperado_cout = 1;
        #1000;

        $display("5) esperado_sum=%b | obtido_soma=%b | %s", esperado_sum, sum, (sum == esperado_sum) ? "OK" : "ERRO");
        $display("5) esperado_cout=%b | obtido_cout=%b | %s", esperado_cout, cout, (cout == esperado_cout) ? "OK" : "ERRO");

        // 6) soma sem overflow e sem cin
        a = 8'b00000011;
        b = 8'b00000001;
        cin = 0;
        esperado_sum = 8'b00000100;
        esperado_cout = 0;
        #1000;

        $display("6) esperado_sum=%b | obtido_soma=%b | %s", esperado_sum, sum, (sum == esperado_sum) ? "OK" : "ERRO");
        $display("6) esperado_cout=%b | obtido_cout=%b | %s", esperado_cout, cout, (cout == esperado_cout) ? "OK" : "ERRO");

        // 7) soma sem overflow e com cin
        a = 8'b00000011;
        b = 8'b00000001;
        cin = 1;
        esperado_sum = 8'b00000101;
        esperado_cout = 0;
        #1000;

        $display("7) esperado_sum=%b | obtido_soma=%b | %s", esperado_sum, sum, (sum == esperado_sum) ? "OK" : "ERRO");
        $display("7) esperado_cout=%b | obtido_cout=%b | %s", esperado_cout, cout, (cout == esperado_cout) ? "OK" : "ERRO");
        

        $finish;
    end
    
    // Monitor para ver os resultados
    initial begin
        $monitor("Tempo: %0t, A=%d, B=%d, Cin=%b, Sum=%d, Cout=%b", 
                 $time, a, b, cin, sum, cout);
    end

endmodule

a16/somador.vcd
$date
	Mon Oct 13 14:20:56 2025
$end
$version
	Icarus Verilog
$end
$timescale
	1s
$end
$scope module tb_carry_lookahead_adder $end
$var wire 8 ! sum [7:0] $end
$var wire 1 " cout $end
$var reg 8 # a [7:0] $end
$var reg 8 $ b [7:0] $end
$var reg 1 % cin $end
$var reg 1 & esperado_cout $end
$var reg 8 ' esperado_sum [7:0] $end
$scope module dut $end
$var wire 8 ( a [7:0] $end
$var wire 8 ) b [7:0] $end
$var wire 1 % cin $end
$var wire 1 " cout $end
$var wire 8 * g [7:0] $end
$var wire 8 + p [7:0] $end
$var wire 8 , sum [7:0] $end
$var wire 8 - c [7:0] $end
$upscope $end
$upscope $end
$enddefinitions $end
$comment Show the parameter values. $end
$dumpall
$end
#0
$dumpvars
bx0 -
bx ,
bx +
bx *
b0 )
b0 (
b0 '
0&
0%
b0 $
b0 #
x"
bx !
$end
#7
b0 *
#8
b0 +
#20
bx0 !
bx0 ,
#22
bx00 -
#23
0"
#29
bx000 -
#36
bx0000 -
#43
bx00000 -
#50
bx000000 -
#61
bx0000000 -
#68
b0 -
#88
b0 !
b0 ,
#1000
1&
b1 -
1%
b11111111 #
b11111111 (
#1008
b11111111 +
#1020
b11111110 !
b11111110 ,
#1023
b11 -
#1030
b111 -
#1037
b1111 -
#1044
b11111 -
#1051
b111111 -
#1062
b1111111 -
#1069
b11111111 -
#1084
1"
#1089
b0 !
b0 ,
#2000
b11111111 $
b11111111 )
b0 #
b0 (
#3000
b11111110 '
b11111110 -
0%
b11111111 #
b11111111 (
#3007
b11111111 *
#3020
b11111110 !
b11111110 ,
#4000
b11111111 '
b11111111 -
1%
#4020
b11111111 !
b11111111 ,
#5000
0&
b100 '
b11111110 -
0%
b1 $
b1 )
b11 #
b11 (
#5007
b1 *
#5008
b11 +
#5020
b11111100 !
b11111100 ,
#5023
0"
#5037
b11110110 -
#5044
b11100110 -
#5051
b11000110 -
#5062
b10000110 -
#5069
b110 -
#5089
b100 !
b100 ,
#6000
b101 '
b111 -
1%
#6020
b101 !
b101 ,
